zapsea/__init__.py
zapsea/__init__.py.bak
zapsea/auth.py
zapsea/client.py
zapsea/config.py
zapsea/config.py.bak
zapsea/exceptions.py
zapsea/types.py
zapsea/resources/__init__.py
zapsea/resources/feedback.py
zapsea/resources/impact.py
zapsea/resources/influence.py
zapsea/resources/jobs.py
zapsea-1.0.0.dist-info/METADATA
zapsea-1.0.0.dist-info/WHEEL
zapsea-1.0.0.dist-info/entry_points.txt
zapsea-1.0.0.dist-info/top_level.txt
zapsea-1.0.0.dist-info/RECORD
